glfw_extended/GLFW.py
glfw_extended/__init__.py
glfw_extended/glfw3.dll
glfw_extended/library.py
glfw_extended/msvcr120.dll
glfw_extended-0.1.0.dist-info/licenses/LICENSE
glfw_extended-0.1.0.dist-info/METADATA
glfw_extended-0.1.0.dist-info/WHEEL
glfw_extended-0.1.0.dist-info/top_level.txt
glfw_extended-0.1.0.dist-info/RECORD
