Metadata-Version: 2.4
Name: glfw-extended
Version: 0.1.0
Summary: Python bindings for TheCherno's GLFW fork with custom titlebar support
Author: Izaiah Meyer
License-Expression: MIT
Project-URL: Homepage, https://github.com/Azaias/glfw-extended
Project-URL: GLFW Fork, https://github.com/TheCherno/glfw
Project-URL: Original pyGLFW, https://github.com/FlorianRhiem/pyGLFW
Keywords: GLFW,OpenGL,Vulkan,window,titlebar,ImGui
Classifier: Development Status :: 4 - Beta
Classifier: Intended Audience :: Developers
Classifier: Operating System :: Microsoft :: Windows
Classifier: Programming Language :: Python :: 3
Classifier: Programming Language :: Python :: 3.8
Classifier: Programming Language :: Python :: 3.9
Classifier: Programming Language :: Python :: 3.10
Classifier: Programming Language :: Python :: 3.11
Classifier: Programming Language :: Python :: 3.12
Classifier: Topic :: Games/Entertainment
Classifier: Topic :: Multimedia :: Graphics
Classifier: Topic :: Software Development :: Libraries :: Python Modules
Requires-Python: >=3.8
License-File: LICENSE
Dynamic: license-file
